[{"package": "requests", "maintainers": ["me@kennethreitz.org"], "last-release": "2020-02-19 18:50:59", "leaks": {"me@kennethreitz.org": {"leakNum": 8, "leakWebsites": ["Apollo", "Artsy", "Canva", "GeekedIn", "OnlinerSpambot", "PDL", "VerificationsIO", "YouveBeenScraped"]}}, "total-leaks": 8, "average-leaks": 8.0, "maintained": true}, {"package": "six", "maintainers": ["benjamin@python.org"], "last-release": "2020-05-21 15:25:54", "leaks": {"benjamin@python.org": {"leakNum": 6, "leakWebsites": ["GeekedIn", "NemoWeb", "OnlinerSpambot", "PDL", "VerificationsIO", "YouveBeenScraped"]}}, "total-leaks": 6, "average-leaks": 6.0, "maintained": true}, {"package": "numpy", "maintainers": ["numpy-discussion@python.org"], "last-release": "2020-06-04 00:10:51", "leaks": {"numpy-discussion@python.org": {"leakNum": 0, "leakWebsites": []}}, "total-leaks": 0, "average-leaks": 0.0, "maintained": true}, {"package": "click", "maintainers": ["contact@palletsprojects.com"], "last-release": "2020-04-27 20:22:42", "leaks": {"contact@palletsprojects.com": {"leakNum": 0, "leakWebsites": []}}, "total-leaks": 0, "average-leaks": 0.0, "maintained": true}, {"package": "PyYAML", "maintainers": ["xi@resolvent.net"], "last-release": "2020-03-18 21:41:00", "leaks": {"xi@resolvent.net": {"leakNum": 12, "leakWebsites": ["AntiPublic", "B2BUSABusinesses", "Disqus", "Lastfm", "LinkedIn", "LiveJournal", "OnlinerSpambot", "PDL", "TrikSpamBotnet", "Tumblr", "VerificationsIO", "YouveBeenScraped"]}}, "total-leaks": 12, "average-leaks": 12.0, "maintained": true}, {"package": "setuptools", "maintainers": ["distutils-sig@python.org"], "last-release": "2020-06-15 20:55:15", "leaks": {"distutils-sig@python.org": {"leakNum": 5, "leakWebsites": ["NemoWeb", "OnlinerSpambot", "PDL", "RiverCityMedia", "VerificationsIO"]}}, "total-leaks": 5, "average-leaks": 5.0, "maintained": true}, {"package": "Django", "maintainers": ["foundation@djangoproject.com"], "last-release": "2020-06-03 09:36:35", "leaks": {"foundation@djangoproject.com": {"leakNum": 1, "leakWebsites": ["OnlinerSpambot"]}}, "total-leaks": 1, "average-leaks": 1.0, "maintained": true}, {"package": "python-dateutil", "maintainers": ["gustavo@niemeyer.net", "dateutil@python.org"], "last-release": "2019-11-03 05:42:01", "leaks": {"gustavo@niemeyer.net": {"leakNum": 15, "leakWebsites": ["AntiPublic", "Bitly", "CafePress", "Disqus", "Dropbox", "ExploitIn", "GeekedIn", "Kickstarter", "LinkedIn", "LiveJournal", "OnlinerSpambot", "PDL", "QuinStreet", "TrikSpamBotnet", "VerificationsIO"]}, "dateutil@python.org": {"leakNum": 0, "leakWebsites": []}}, "total-leaks": 15, "average-leaks": 7.5, "maintained": true}, {"package": "Flask", "maintainers": ["contact@palletsprojects.com", "armin.ronacher@active-4.com"], "last-release": "2020-04-03 17:17:53", "leaks": {"contact@palletsprojects.com": {"leakNum": 0, "leakWebsites": []}, "armin.ronacher@active-4.com": {"leakNum": 18, "leakWebsites": ["2844Breaches", "500px", "Adobe", "Bitly", "Collection1", "Disqus", "Dropbox", "EpicGames", "GeekedIn", "HeroesOfNewerth", "Kickstarter", "LinkedIn", "OnlinerSpambot", "Patreon", "PDL", "Tumblr", "VerificationsIO", "WarInc"]}}, "total-leaks": 18, "average-leaks": 9.0, "maintained": true}, {"package": "Jinja2", "maintainers": ["contact@palletsprojects.com", "armin.ronacher@active-4.com"], "last-release": "2020-04-13 16:16:44", "leaks": {"contact@palletsprojects.com": {"leakNum": 0, "leakWebsites": []}, "armin.ronacher@active-4.com": {"leakNum": 18, "leakWebsites": ["2844Breaches", "500px", "Adobe", "Bitly", "Collection1", "Disqus", "Dropbox", "EpicGames", "GeekedIn", "HeroesOfNewerth", "Kickstarter", "LinkedIn", "OnlinerSpambot", "Patreon", "PDL", "Tumblr", "VerificationsIO", "WarInc"]}}, "total-leaks": 18, "average-leaks": 9.0, "maintained": true}, {"package": "lxml", "maintainers": ["lxml-dev@lxml.de"], "last-release": "2020-05-19 10:00:15", "leaks": {"lxml-dev@lxml.de": {"leakNum": 1, "leakWebsites": ["OnlinerSpambot"]}}, "total-leaks": 1, "average-leaks": 1.0, "maintained": true}, {"package": "urllib3", "maintainers": ["andrey.petrov@shazow.net"], "last-release": "2020-04-16 15:44:06", "leaks": {"andrey.petrov@shazow.net": {"leakNum": 10, "leakWebsites": ["500px", "Apollo", "BTCE", "GeekedIn", "OnlinerSpambot", "Patreon", "PDL", "Ticketfly", "VerificationsIO", "YouveBeenScraped"]}}, "total-leaks": 10, "average-leaks": 10.0, "maintained": true}, {"package": "pandas", "maintainers": ["pydata@googlegroups.com"], "last-release": "2020-05-29 11:49:40", "leaks": {"pydata@googlegroups.com": {"leakNum": 3, "leakWebsites": ["NemoWeb", "OnlinerSpambot", "VerificationsIO"]}}, "total-leaks": 3, "average-leaks": 3.0, "maintained": true}, {"package": "beautifulsoup4", "maintainers": ["leonardr@segfault.org"], "last-release": "2020-05-17 18:24:02", "leaks": {"leonardr@segfault.org": {"leakNum": 14, "leakWebsites": ["AntiPublic", "B2BUSABusinesses", "Bitly", "Dropbox", "Kickstarter", "Lastfm", "LeadHunter", "LinkedIn", "OnlinerSpambot", "Patreon", "PDL", "VerificationsIO", "YouveBeenScraped", "Zynga"]}}, "total-leaks": 14, "average-leaks": 14.0, "maintained": true}, {"package": "future", "maintainers": ["ed@pythoncharmers.com"], "last-release": "2019-10-31 00:58:13", "leaks": {"ed@pythoncharmers.com": {"leakNum": 11, "leakWebsites": ["Adobe", "Apollo", "Bitly", "BTCE", "Disqus", "Dropbox", "GeekedIn", "LeadHunter", "LuminPDF", "OnlinerSpambot", "PDL"]}}, "total-leaks": 11, "average-leaks": 11.0, "maintained": true}, {"package": "boto3", "maintainers": [], "last-release": "2020-06-16 19:17:40", "leaks": {}, "total-leaks": 0, "average-leaks": 0.0, "maintained": true}, {"package": "pytest", "maintainers": [], "last-release": "2020-06-02 16:43:41", "leaks": {}, "total-leaks": 0, "average-leaks": 0.0, "maintained": true}, {"package": "Pillow", "maintainers": ["aclark@python-pillow.org"], "last-release": "2020-04-25 18:34:51", "leaks": {"aclark@python-pillow.org": {"leakNum": 1, "leakWebsites": ["GeekedIn"]}}, "total-leaks": 1, "average-leaks": 1.0, "maintained": true}, {"package": "pytz", "maintainers": ["stuart@stuartbishop.net"], "last-release": "2020-04-28 08:28:21", "leaks": {"stuart@stuartbishop.net": {"leakNum": 13, "leakWebsites": ["2844Breaches", "Apollo", "Collection1", "Exactis", "LeadHunter", "LinkedIn", "NetProspex", "NexusMods", "OnlinerSpambot", "PDL", "TheTVDB", "VerificationsIO", "WeHeartIt"]}}, "total-leaks": 13, "average-leaks": 13.0, "maintained": true}, {"package": "tqdm", "maintainers": ["python.tqdm@gmail.com"], "last-release": "2020-06-03 10:16:10", "leaks": {"python.tqdm@gmail.com": {"leakNum": 1, "leakWebsites": ["GeekedIn"]}}, "total-leaks": 1, "average-leaks": 1.0, "maintained": true}, {"package": "certifi", "maintainers": ["me@kennethreitz.com"], "last-release": "2020-06-07 09:36:44", "leaks": {"me@kennethreitz.com": {"leakNum": 32, "leakWebsites": ["500px", "Adobe", "AntiPublic", "Apollo", "Artsy", "Bitly", "CafePress", "Collection1", "Dailymotion", "Disqus", "Dropbox", "Elance", "ExploitIn", "Gawker", "Kickstarter", "Lastfm", "LinkedIn", "MailRu", "MySpace", "OnlinerSpambot", "PDL", "Pemiblanc", "QuinStreet", "RiverCityMedia", "ShareThis", "Ticketfly", "TrikSpamBotnet", "Trillian", "Tumblr", "VerificationsIO", "Yahoo", "YouveBeenScraped"]}}, "total-leaks": 32, "average-leaks": 32.0, "maintained": true}, {"package": "SQLAlchemy", "maintainers": ["mike_mp@zzzcomputing.com"], "last-release": "2020-05-14 08:49:19", "leaks": {"mike_mp@zzzcomputing.com": {"leakNum": 7, "leakWebsites": ["B2BUSABusinesses", "db8151dd", "Disqus", "LinkedIn", "OnlinerSpambot", "PDL", "YouveBeenScraped"]}}, "total-leaks": 7, "average-leaks": 7.0, "maintained": true}, {"package": "scipy", "maintainers": ["scipy-dev@python.org"], "last-release": "2019-12-19 15:45:51", "leaks": {"scipy-dev@python.org": {"leakNum": 0, "leakWebsites": []}}, "total-leaks": 0, "average-leaks": 0.0, "maintained": true}, {"package": "matplotlib", "maintainers": ["matplotlib-users@python.org"], "last-release": "2020-03-18 22:06:38", "leaks": {"matplotlib-users@python.org": {"leakNum": 1, "leakWebsites": ["OnlinerSpambot"]}}, "total-leaks": 1, "average-leaks": 1.0, "maintained": true}, {"package": "colorama", "maintainers": ["tartley@tartley.com"], "last-release": "2019-12-06 20:46:31", "leaks": {"tartley@tartley.com": {"leakNum": 18, "leakWebsites": ["AdultFriendFinder2016", "DaniWeb", "db8151dd", "Disqus", "Dropbox", "Gawker", "GeekedIn", "Lastfm", "LinkedIn", "MySpace", "NemoWeb", "OnlinerSpambot", "PDL", "Pemiblanc", "TrikSpamBotnet", "VerificationsIO", "XKCD", "Zynga"]}}, "total-leaks": 18, "average-leaks": 18.0, "maintained": true}, {"package": "cryptography", "maintainers": ["cryptography-dev@python.org"], "last-release": "2020-04-22 23:19:51", "leaks": {"cryptography-dev@python.org": {"leakNum": 2, "leakWebsites": ["NemoWeb", "OnlinerSpambot"]}}, "total-leaks": 2, "average-leaks": 2.0, "maintained": true}, {"package": "attrs", "maintainers": ["hs@ox.cx"], "last-release": "2019-10-15 05:52:40", "leaks": {"hs@ox.cx": {"leakNum": 21, "leakWebsites": ["500px", "Adobe", "Bitly", "Dailymotion", "Disqus", "Dropbox", "GeekedIn", "Kickstarter", "Lastfm", "LinkedIn", "MyFitnessPal", "MyHeritage", "NemoWeb", "OnlinerSpambot", "PDL", "TrikSpamBotnet", "Trillian", "Tumblr", "VerificationsIO", "YouveBeenScraped", "Zynga"]}}, "total-leaks": 21, "average-leaks": 21.0, "maintained": true}, {"package": "psutil", "maintainers": ["g.rodola@gmail.com"], "last-release": "2020-02-18 18:02:31", "leaks": {"g.rodola@gmail.com": {"leakNum": 13, "leakWebsites": ["Badoo", "Collection1", "Dropbox", "ExploitIn", "GeekedIn", "LinkedIn", "LinuxMint", "MyHeritage", "NemoWeb", "OnlinerSpambot", "PDL", "YouveBeenScraped", "Zoosk"]}}, "total-leaks": 13, "average-leaks": 13.0, "maintained": true}, {"package": "aiohttp", "maintainers": ["fafhrd91@gmail.com", "aio-libs@googlegroups.com"], "last-release": "2019-10-09 16:54:45", "leaks": {"fafhrd91@gmail.com": {"leakNum": 10, "leakWebsites": ["Adobe", "Apollo", "CDProjektRed", "Collection1", "Dropbox", "GeekedIn", "KayoMoe", "LinkedIn", "PDL", "Ticketfly"]}, "aio-libs@googlegroups.com": {"leakNum": 0, "leakWebsites": []}}, "total-leaks": 10, "average-leaks": 5.0, "maintained": true}, {"package": "docopt", "maintainers": ["vladimir@keleshev.com"], "last-release": "2014-06-16 11:18:57", "leaks": {"vladimir@keleshev.com": {"leakNum": 2, "leakWebsites": ["GeekedIn", "VerificationsIO"]}}, "total-leaks": 2, "average-leaks": 2.0, "maintained": false}, {"package": "redis", "maintainers": ["sedrik@gmail.com"], "last-release": "2020-06-01 21:30:33", "leaks": {"sedrik@gmail.com": {"leakNum": 12, "leakWebsites": ["2844Breaches", "Canva", "Collection1", "Disqus", "Dropbox", "ExploitIn", "GeekedIn", "HeroesOfNewerth", "Kickstarter", "PDL", "VerificationsIO", "Zynga"]}}, "total-leaks": 12, "average-leaks": 12.0, "maintained": true}, {"package": "enum34", "maintainers": ["ethan@stoneleaf.us"], "last-release": "2020-03-10 17:47:58", "leaks": {"ethan@stoneleaf.us": {"leakNum": 8, "leakWebsites": ["AntiPublic", "LinkedIn", "NemoWeb", "OnlinerSpambot", "PDL", "VerificationsIO", "YouveBeenScraped", "Zomato"]}}, "total-leaks": 8, "average-leaks": 8.0, "maintained": true}, {"package": "jsonschema", "maintainers": ["Julian@GrayVines.com"], "last-release": "2019-11-18 12:57:08", "leaks": {"Julian@GrayVines.com": {"leakNum": 0, "leakWebsites": []}}, "total-leaks": 0, "average-leaks": 0.0, "maintained": true}, {"package": "Pygments", "maintainers": ["georg@python.org"], "last-release": "2020-03-09 08:17:53", "leaks": {"georg@python.org": {"leakNum": 6, "leakWebsites": ["Apollo", "Disqus", "GeekedIn", "NemoWeb", "OnlinerSpambot", "PDL"]}}, "total-leaks": 6, "average-leaks": 6.0, "maintained": true}, {"package": "bs4", "maintainers": ["leonardr@segfault.org"], "last-release": "2016-03-03 13:25:12", "leaks": {"leonardr@segfault.org": {"leakNum": 14, "leakWebsites": ["AntiPublic", "B2BUSABusinesses", "Bitly", "Dropbox", "Kickstarter", "Lastfm", "LeadHunter", "LinkedIn", "OnlinerSpambot", "Patreon", "PDL", "VerificationsIO", "YouveBeenScraped", "Zynga"]}}, "total-leaks": 14, "average-leaks": 14.0, "maintained": false}, {"package": "tabulate", "maintainers": ["s.astanin@gmail.com"], "last-release": "2020-03-22 17:02:41", "leaks": {"s.astanin@gmail.com": {"leakNum": 12, "leakWebsites": ["Adobe", "Collection1", "Dailymotion", "Disqus", "Dropbox", "GeekedIn", "Kickstarter", "LinkedIn", "LinuxMint", "LiveJournal", "ShareThis", "Tumblr"]}}, "total-leaks": 12, "average-leaks": 12.0, "maintained": true}, {"package": "protobuf", "maintainers": ["protobuf@googlegroups.com"], "last-release": "2020-05-27 18:02:19", "leaks": {"protobuf@googlegroups.com": {"leakNum": 2, "leakWebsites": ["OnlinerSpambot", "VerificationsIO"]}}, "total-leaks": 2, "average-leaks": 2.0, "maintained": true}, {"package": "chardet", "maintainers": ["dan.blanchard@gmail.com"], "last-release": "2017-06-08 14:34:33", "leaks": {"dan.blanchard@gmail.com": {"leakNum": 30, "leakWebsites": ["2844Breaches", "8tracks", "Adobe", "Bitly", "CDProjektRed", "CheapAssGamer", "Collection1", "DataAndLeads", "Disqus", "Dropbox", "Evite", "Exactis", "ExploitIn", "Fling", "GeekedIn", "HauteLook", "Kickstarter", "Lastfm", "LeadHunter", "LinkedIn", "NexusMods", "OnlinerSpambot", "PDL", "Pemiblanc", "Plex", "RiverCityMedia", "SCDailyPhoneSpamList", "ShareThis", "VerificationsIO", "Zynga"]}}, "total-leaks": 30, "average-leaks": 30.0, "maintained": false}, {"package": "GitPython", "maintainers": ["byronimo@gmail.com, mtrier@gmail.com"], "last-release": "2020-05-31 03:25:14", "leaks": {"byronimo@gmail.com, mtrier@gmail.com": {"leakNum": 0, "leakWebsites": []}}, "total-leaks": 0, "average-leaks": 0.0, "maintained": true}, {"package": "appdirs", "maintainers": ["jr@its.to", "trentm@gmail.com"], "last-release": "2020-05-11 07:59:49", "leaks": {"jr@its.to": {"leakNum": 10, "leakWebsites": ["AntiPublic", "CafePress", "Creative", "Dropbox", "ExploitIn", "Kickstarter", "LinkedIn", "MoneyBookers", "PDL", "VerificationsIO"]}, "trentm@gmail.com": {"leakNum": 24, "leakWebsites": ["Adobe", "AerServ", "Animoto", "Bitly", "Collection1", "Disqus", "Dropbox", "Dubsmash", "Evite", "Evony", "Exactis", "GeekedIn", "HauteLook", "Lastfm", "Leet", "LinkedIn", "Mathway", "MyHeritage", "OnlinerSpambot", "PDL", "RiverCityMedia", "Tumblr", "VerificationsIO", "YouveBeenScraped"]}}, "total-leaks": 34, "average-leaks": 17.0, "maintained": true}, {"package": "PyJWT", "maintainers": ["hello@jpadilla.com"], "last-release": "2018-12-07 13:40:06", "leaks": {"hello@jpadilla.com": {"leakNum": 2, "leakWebsites": ["OnlinerSpambot", "PDL"]}}, "total-leaks": 2, "average-leaks": 2.0, "maintained": false}, {"package": "selenium", "maintainers": [], "last-release": "2018-11-01 09:01:35", "leaks": {}, "total-leaks": 0, "average-leaks": 0.0, "maintained": false}, {"package": "idna", "maintainers": ["kim@cynosure.com.au"], "last-release": "2020-02-17 07:07:32", "leaks": {"kim@cynosure.com.au": {"leakNum": 19, "leakWebsites": ["500px", "Adobe", "AntiPublic", "Collection1", "Dropbox", "ExploitIn", "KayoMoe", "Kickstarter", "Lastfm", "LeadHunter", "LinkedIn", "LiveJournal", "MySpace", "OnlinerSpambot", "PDL", "TrikSpamBotnet", "Tumblr", "VerificationsIO", "Zynga"]}}, "total-leaks": 19, "average-leaks": 19.0, "maintained": true}, {"package": "Sphinx", "maintainers": ["georg@python.org"], "last-release": "2020-06-14 03:54:18", "leaks": {"georg@python.org": {"leakNum": 6, "leakWebsites": ["Apollo", "Disqus", "GeekedIn", "NemoWeb", "OnlinerSpambot", "PDL"]}}, "total-leaks": 6, "average-leaks": 6.0, "maintained": true}, {"package": "tornado", "maintainers": ["python-tornado@googlegroups.com"], "last-release": "2020-03-04 02:32:23", "leaks": {"python-tornado@googlegroups.com": {"leakNum": 2, "leakWebsites": ["OnlinerSpambot", "VerificationsIO"]}}, "total-leaks": 2, "average-leaks": 2.0, "maintained": true}, {"package": "Markdown", "maintainers": ["waylan.limberg@icloud.com"], "last-release": "2020-05-08 17:24:36", "leaks": {"waylan.limberg@icloud.com": {"leakNum": 2, "leakWebsites": ["db8151dd", "GeekedIn"]}}, "total-leaks": 2, "average-leaks": 2.0, "maintained": true}, {"package": "simplejson", "maintainers": ["bob@redivi.com"], "last-release": "2019-11-18 06:43:55", "leaks": {"bob@redivi.com": {"leakNum": 33, "leakWebsites": ["2844Breaches", "Adobe", "AntiPublic", "Apollo", "B2BUSABusinesses", "Bitly", "Canva", "Collection1", "db8151dd", "Disqus", "Dropbox", "Evite", "ExploitIn", "GameSalad", "GateHub", "GeekedIn", "Houzz", "Kickstarter", "Lastfm", "LinkedIn", "LiveJournal", "MyFitnessPal", "NetEase", "NetProspex", "OnlinerSpambot", "PDL", "RiverCityMedia", "Ticketfly", "TrikSpamBotnet", "Tumblr", "VerificationsIO", "VK", "Zynga"]}}, "total-leaks": 33, "average-leaks": 33.0, "maintained": true}, {"package": "pbr", "maintainers": ["openstack-discuss@lists.openstack.org"], "last-release": "2020-04-07 10:08:23", "leaks": {"openstack-discuss@lists.openstack.org": {"leakNum": 0, "leakWebsites": []}}, "total-leaks": 0, "average-leaks": 0.0, "maintained": true}, {"package": "typing-extensions", "maintainers": ["levkivskyi@gmail.com"], "last-release": "2020-04-02 17:40:28", "leaks": {"levkivskyi@gmail.com": {"leakNum": 4, "leakWebsites": ["Collection1", "Dropbox", "ExploitIn", "VK"]}}, "total-leaks": 4, "average-leaks": 4.0, "maintained": true}, {"package": "networkx", "maintainers": ["networkx-discuss@googlegroups.com", "hagberg@lanl.gov"], "last-release": "2019-10-17 02:07:15", "leaks": {"networkx-discuss@googlegroups.com": {"leakNum": 2, "leakWebsites": ["OnlinerSpambot", "VerificationsIO"]}, "hagberg@lanl.gov": {"leakNum": 6, "leakWebsites": ["Apollo", "Evite", "Exactis", "NetProspex", "PDL", "VerificationsIO"]}}, "total-leaks": 8, "average-leaks": 4.0, "maintained": true}, {"package": "mock", "maintainers": ["testing-in-python@lists.idyll.org"], "last-release": "2020-03-11 17:28:56", "leaks": {"testing-in-python@lists.idyll.org": {"leakNum": 2, "leakWebsites": ["NemoWeb", "OnlinerSpambot"]}}, "total-leaks": 2, "average-leaks": 2.0, "maintained": true}, {"package": "configparser", "maintainers": ["jaraco@jaraco.com", "lukasz@langa.pl"], "last-release": "2020-03-26 00:07:02", "leaks": {"jaraco@jaraco.com": {"leakNum": 27, "leakWebsites": ["Adobe", "AntiPublic", "Apollo", "Bitly", "CafePress", "Collection1", "Dailymotion", "Dropbox", "ExploitIn", "GeekedIn", "Kickstarter", "Lastfm", "LinkedIn", "LiveJournal", "MoDaCo", "MyFitnessPal", "MyHeritage", "MySpace", "NetEase", "OnlinerSpambot", "Patreon", "PDL", "QuinStreet", "Trillian", "VerificationsIO", "Xbox-Scene", "YouNow"]}, "lukasz@langa.pl": {"leakNum": 11, "leakWebsites": ["Adobe", "CafePress", "Dropbox", "GeekedIn", "Lastfm", "MyFitnessPal", "OnlinerSpambot", "Reverb-Nation", "ShareThis", "VerificationsIO", "Zynga"]}}, "total-leaks": 38, "average-leaks": 19.0, "maintained": true}, {"package": "djangorestframework", "maintainers": ["tom@tomchristie.com"], "last-release": "2019-12-12 14:50:25", "leaks": {"tom@tomchristie.com": {"leakNum": 20, "leakWebsites": ["AntiPublic", "Artsy", "Bitly", "Collection1", "Dropbox", "Evite", "ExploitIn", "GeekedIn", "Houzz", "Kickstarter", "Lastfm", "LeadHunter", "LinkedIn", "MySpace", "OnlinerSpambot", "Patreon", "PDL", "TrikSpamBotnet", "VerificationsIO", "Zynga"]}}, "total-leaks": 20, "average-leaks": 20.0, "maintained": true}, {"package": "pymongo", "maintainers": ["bernie@mongodb.com"], "last-release": "2020-01-08 01:16:33", "leaks": {"bernie@mongodb.com": {"leakNum": 3, "leakWebsites": ["Adapt", "Apollo", "OnlinerSpambot"]}}, "total-leaks": 3, "average-leaks": 3.0, "maintained": true}, {"package": "toml", "maintainers": ["uiri@xqz.ca"], "last-release": "2020-05-14 03:56:07", "leaks": {"uiri@xqz.ca": {"leakNum": 0, "leakWebsites": []}}, "total-leaks": 0, "average-leaks": 0.0, "maintained": true}, {"package": "PyMySQL", "maintainers": ["yutaka.matsubara@gmail.com", "songofacandy@gmail.com"], "last-release": "2018-12-18 11:41:04", "leaks": {"yutaka.matsubara@gmail.com": {"leakNum": 12, "leakWebsites": ["8tracks", "Adobe", "Collection1", "Dropbox", "ExploitIn", "GeekedIn", "imgur", "Lastfm", "LinkedIn", "NexusMods", "PDL", "Tumblr"]}, "songofacandy@gmail.com": {"leakNum": 4, "leakWebsites": ["Dailymotion", "Dropbox", "NemoWeb", "OnlinerSpambot"]}}, "total-leaks": 16, "average-leaks": 8.0, "maintained": false}, {"package": "Werkzeug", "maintainers": ["contact@palletsprojects.com", "armin.ronacher@active-4.com"], "last-release": "2020-03-31 18:03:34", "leaks": {"contact@palletsprojects.com": {"leakNum": 0, "leakWebsites": []}, "armin.ronacher@active-4.com": {"leakNum": 18, "leakWebsites": ["2844Breaches", "500px", "Adobe", "Bitly", "Collection1", "Disqus", "Dropbox", "EpicGames", "GeekedIn", "HeroesOfNewerth", "Kickstarter", "LinkedIn", "OnlinerSpambot", "Patreon", "PDL", "Tumblr", "VerificationsIO", "WarInc"]}}, "total-leaks": 18, "average-leaks": 9.0, "maintained": true}, {"package": "typing", "maintainers": ["jukka.lehtosalo@iki.fi"], "last-release": "2019-08-22 13:37:11", "leaks": {"jukka.lehtosalo@iki.fi": {"leakNum": 0, "leakWebsites": []}}, "total-leaks": 0, "average-leaks": 0.0, "maintained": true}, {"package": "docker", "maintainers": ["joffrey@docker.com"], "last-release": "2020-06-02 14:17:59", "leaks": {"joffrey@docker.com": {"leakNum": 2, "leakWebsites": ["Adapt", "Apollo"]}}, "total-leaks": 2, "average-leaks": 2.0, "maintained": true}, {"package": "wheel", "maintainers": ["dholth@fastmail.fm", "alex.gronholm@nextday.fi"], "last-release": "2020-01-30 22:22:49", "leaks": {"dholth@fastmail.fm": {"leakNum": 11, "leakWebsites": ["AntiPublic", "Boxee", "Dropbox", "Gawker", "GeekedIn", "Lastfm", "LinkedIn", "MySpace", "OnlinerSpambot", "PDL", "YouveBeenScraped"]}, "alex.gronholm@nextday.fi": {"leakNum": 6, "leakWebsites": ["AntiPublic", "LinkedIn", "OnlinerSpambot", "PDL", "TrikSpamBotnet", "YouveBeenScraped"]}}, "total-leaks": 17, "average-leaks": 8.5, "maintained": true}, {"package": "argparse", "maintainers": ["tw@waldmann-edv.de"], "last-release": "2015-09-14 16:03:16", "leaks": {"tw@waldmann-edv.de": {"leakNum": 3, "leakWebsites": ["GeekedIn", "PDL", "VerificationsIO"]}}, "total-leaks": 3, "average-leaks": 3.0, "maintained": false}, {"package": "pyserial", "maintainers": ["cliechti@gmx.net"], "last-release": "2017-07-23 21:10:01", "leaks": {"cliechti@gmx.net": {"leakNum": 2, "leakWebsites": ["NemoWeb", "OnlinerSpambot"]}}, "total-leaks": 2, "average-leaks": 2.0, "maintained": false}, {"package": "pyOpenSSL", "maintainers": ["cryptography-dev@python.org"], "last-release": "2019-11-18 04:59:37", "leaks": {"cryptography-dev@python.org": {"leakNum": 2, "leakWebsites": ["NemoWeb", "OnlinerSpambot"]}}, "total-leaks": 2, "average-leaks": 2.0, "maintained": true}, {"package": "ruamel.yaml", "maintainers": ["a.van.der.neut@ruamel.eu"], "last-release": "2020-02-12 12:41:44", "leaks": {"a.van.der.neut@ruamel.eu": {"leakNum": 4, "leakWebsites": ["LeadHunter", "NemoWeb", "PDL", "VerificationsIO"]}}, "total-leaks": 4, "average-leaks": 4.0, "maintained": true}, {"package": "nose", "maintainers": ["jpellerin+nose@gmail.com"], "last-release": "2015-06-02 09:12:36", "leaks": {"jpellerin+nose@gmail.com": {"leakNum": 0, "leakWebsites": []}}, "total-leaks": 0, "average-leaks": 0.0, "maintained": false}, {"package": "docutils", "maintainers": ["goodger@python.org", "docutils-develop@lists.sourceforge.net"], "last-release": "2020-01-12 13:55:21", "leaks": {"goodger@python.org": {"leakNum": 11, "leakWebsites": ["Adobe", "AntiPublic", "CafePress", "ExploitIn", "Gawker", "LinkedIn", "OnlinerSpambot", "PDL", "RiverCityMedia", "VerificationsIO", "YouveBeenScraped"]}, "docutils-develop@lists.sourceforge.net": {"leakNum": 2, "leakWebsites": ["PDL", "VerificationsIO"]}}, "total-leaks": 13, "average-leaks": 6.5, "maintained": true}, {"package": "dataclasses", "maintainers": ["eric@python.org"], "last-release": "2019-10-20 18:01:36", "leaks": {"eric@python.org": {"leakNum": 0, "leakWebsites": []}}, "total-leaks": 0, "average-leaks": 0.0, "maintained": true}, {"package": "pyparsing", "maintainers": ["ptmcg@users.sourceforge.net"], "last-release": "2020-04-05 22:21:22", "leaks": {"ptmcg@users.sourceforge.net": {"leakNum": 0, "leakWebsites": []}}, "total-leaks": 0, "average-leaks": 0.0, "maintained": true}, {"package": "botocore", "maintainers": [], "last-release": "2020-06-16 19:17:34", "leaks": {}, "total-leaks": 0, "average-leaks": 0.0, "maintained": true}, {"package": "packaging", "maintainers": ["donald@stufft.io"], "last-release": "2020-05-19 06:30:05", "leaks": {"donald@stufft.io": {"leakNum": 8, "leakWebsites": ["Apollo", "Dropbox", "Facepunch", "GeekedIn", "NemoWeb", "OnlinerSpambot", "PDL", "YouveBeenScraped"]}}, "total-leaks": 8, "average-leaks": 8.0, "maintained": true}, {"package": "marshmallow", "maintainers": ["sloria1@gmail.com"], "last-release": "2020-06-02 20:36:13", "leaks": {"sloria1@gmail.com": {"leakNum": 18, "leakWebsites": ["2844Breaches", "Adobe", "Bitly", "Chegg", "Collection1", "Dailymotion", "db8151dd", "Dropbox", "EatStreet", "Evite", "GeekedIn", "gPotato", "Lastfm", "LinkedIn", "OnlinerSpambot", "PDL", "VerificationsIO", "Zynga"]}}, "total-leaks": 18, "average-leaks": 18.0, "maintained": true}, {"package": "gevent", "maintainers": ["denis.bilenko@gmail.com", "jason@nextthought.com"], "last-release": "2020-06-16 14:48:09", "leaks": {"denis.bilenko@gmail.com": {"leakNum": 13, "leakWebsites": ["ArmorGames", "Bitly", "Disqus", "Dropbox", "Elance", "ExploitIn", "GeekedIn", "Lastfm", "LinkedIn", "LiveJournal", "OnlinerSpambot", "PDL", "Tumblr"]}, "jason@nextthought.com": {"leakNum": 3, "leakWebsites": ["GeekedIn", "NetProspex", "VerificationsIO"]}}, "total-leaks": 16, "average-leaks": 8.0, "maintained": true}, {"package": "arrow", "maintainers": ["crsmithdev@gmail.com"], "last-release": "2020-05-03 10:54:10", "leaks": {"crsmithdev@gmail.com": {"leakNum": 15, "leakWebsites": ["500px", "Adobe", "B2BUSABusinesses", "Bitly", "Collection1", "Dropbox", "Evite", "ExploitIn", "GeekedIn", "LinkedIn", "PDL", "Tumblr", "VerificationsIO", "YouveBeenScraped", "Zoosk"]}}, "total-leaks": 15, "average-leaks": 15.0, "maintained": true}, {"package": "google-api-python-client", "maintainers": ["googleapis-packages@google.com"], "last-release": "2020-06-11 02:36:27", "leaks": {"googleapis-packages@google.com": {"leakNum": 0, "leakWebsites": []}}, "total-leaks": 0, "average-leaks": 0.0, "maintained": true}, {"package": "paramiko", "maintainers": ["jeff@bitprophet.org"], "last-release": "2019-12-09 23:21:54", "leaks": {"jeff@bitprophet.org": {"leakNum": 16, "leakWebsites": ["AntiPublic", "Apollo", "CheapAssGamer", "Disqus", "Dropbox", "Evite", "Exactis", "GeekedIn", "Kickstarter", "Lastfm", "LinkedIn", "OnlinerSpambot", "Patreon", "PDL", "VerificationsIO", "YouveBeenScraped"]}}, "total-leaks": 16, "average-leaks": 16.0, "maintained": true}, {"package": "ipython", "maintainers": ["ipython-dev@python.org"], "last-release": "2020-05-29 22:49:53", "leaks": {"ipython-dev@python.org": {"leakNum": 0, "leakWebsites": []}}, "total-leaks": 0, "average-leaks": 0.0, "maintained": true}, {"package": "websocket-client", "maintainers": ["liris.pp@gmail.com"], "last-release": "2019-12-25 12:46:58", "leaks": {"liris.pp@gmail.com": {"leakNum": 12, "leakWebsites": ["Adobe", "Badoo", "Collection1", "Dropbox", "ExploitIn", "GeekedIn", "Lastfm", "LinkedIn", "OnlinerSpambot", "PDL", "Tumblr", "YouveBeenScraped"]}}, "total-leaks": 12, "average-leaks": 12.0, "maintained": true}, {"package": "scikit-learn", "maintainers": ["amueller@ais.uni-bonn.de"], "last-release": "2020-05-19 19:24:42", "leaks": {"amueller@ais.uni-bonn.de": {"leakNum": 5, "leakWebsites": ["Bitly", "Dropbox", "GeekedIn", "OnlinerSpambot", "VerificationsIO"]}}, "total-leaks": 5, "average-leaks": 5.0, "maintained": true}, {"package": "grpcio", "maintainers": ["grpc-io@googlegroups.com"], "last-release": "2020-05-14 17:48:58", "leaks": {"grpc-io@googlegroups.com": {"leakNum": 1, "leakWebsites": ["GeekedIn"]}}, "total-leaks": 1, "average-leaks": 1.0, "maintained": true}, {"package": "openpyxl", "maintainers": ["charlie.clark@clark-consulting.eu"], "last-release": "2020-01-10 16:45:28", "leaks": {"charlie.clark@clark-consulting.eu": {"leakNum": 5, "leakWebsites": ["Apollo", "GeekedIn", "LinkedIn", "PDL", "YouveBeenScraped"]}}, "total-leaks": 5, "average-leaks": 5.0, "maintained": true}, {"package": "cffi", "maintainers": ["python-cffi@googlegroups.com"], "last-release": "2020-02-07 15:44:28", "leaks": {"python-cffi@googlegroups.com": {"leakNum": 2, "leakWebsites": ["NemoWeb", "OnlinerSpambot"]}}, "total-leaks": 2, "average-leaks": 2.0, "maintained": true}, {"package": "pycryptodome", "maintainers": ["helderijs@gmail.com"], "last-release": "2020-02-21 07:22:51", "leaks": {"helderijs@gmail.com": {"leakNum": 1, "leakWebsites": ["GeekedIn"]}}, "total-leaks": 1, "average-leaks": 1.0, "maintained": true}, {"package": "pip", "maintainers": ["pypa-dev@groups.google.com"], "last-release": "2020-05-19 10:40:29", "leaks": {"pypa-dev@groups.google.com": {"leakNum": 0, "leakWebsites": []}}, "total-leaks": 0, "average-leaks": 0.0, "maintained": true}, {"package": "futures", "maintainers": ["brian@sweetapp.com", "alex.gronholm@nextday.fi"], "last-release": "2019-07-15 09:33:00", "leaks": {"brian@sweetapp.com": {"leakNum": 16, "leakWebsites": ["Adobe", "CafePress", "Dailymotion", "Dropbox", "Evite", "GeekedIn", "LinkedIn", "MoneyBookers", "MyFitnessPal", "NetProspex", "OnlinerSpambot", "PDL", "RiverCityMedia", "TrikSpamBotnet", "VerificationsIO", "YouveBeenScraped"]}, "alex.gronholm@nextday.fi": {"leakNum": 6, "leakWebsites": ["AntiPublic", "LinkedIn", "OnlinerSpambot", "PDL", "TrikSpamBotnet", "YouveBeenScraped"]}}, "total-leaks": 22, "average-leaks": 11.0, "maintained": true}, {"package": "Babel", "maintainers": ["armin.ronacher@active-4.com"], "last-release": "2019-12-31 12:41:07", "leaks": {"armin.ronacher@active-4.com": {"leakNum": 18, "leakWebsites": ["2844Breaches", "500px", "Adobe", "Bitly", "Collection1", "Disqus", "Dropbox", "EpicGames", "GeekedIn", "HeroesOfNewerth", "Kickstarter", "LinkedIn", "OnlinerSpambot", "Patreon", "PDL", "Tumblr", "VerificationsIO", "WarInc"]}}, "total-leaks": 18, "average-leaks": 18.0, "maintained": true}, {"package": "celery", "maintainers": ["auvipy@gmail.com"], "last-release": "2020-06-08 06:07:37", "leaks": {"auvipy@gmail.com": {"leakNum": 3, "leakWebsites": ["8fit", "Apollo", "GeekedIn"]}}, "total-leaks": 3, "average-leaks": 3.0, "maintained": true}, {"package": "python-dotenv", "maintainers": ["me+github@saurabh-kumar.com"], "last-release": "2020-04-16 21:46:30", "leaks": {"me+github@saurabh-kumar.com": {"leakNum": 0, "leakWebsites": []}}, "total-leaks": 0, "average-leaks": 0.0, "maintained": true}, {"package": "zope.interface", "maintainers": ["zope-dev@zope.org"], "last-release": "2020-04-08 12:39:10", "leaks": {"zope-dev@zope.org": {"leakNum": 2, "leakWebsites": ["OnlinerSpambot", "VerificationsIO"]}}, "total-leaks": 2, "average-leaks": 2.0, "maintained": true}, {"package": "flake8", "maintainers": ["tarek@ziade.org", "graffatcolmingov@gmail.com"], "last-release": "2020-06-08 19:30:37", "leaks": {"tarek@ziade.org": {"leakNum": 9, "leakWebsites": ["2844Breaches", "500px", "Adobe", "Collection1", "Disqus", "Dropbox", "OnlinerSpambot", "OVH", "YouveBeenScraped"]}, "graffatcolmingov@gmail.com": {"leakNum": 5, "leakWebsites": ["Chegg", "GeekedIn", "MyFitnessPal", "NemoWeb", "OnlinerSpambot"]}}, "total-leaks": 14, "average-leaks": 7.0, "maintained": true}, {"package": "boto", "maintainers": ["mitch@garnaat.com"], "last-release": "2018-07-11 20:58:55", "leaks": {"mitch@garnaat.com": {"leakNum": 13, "leakWebsites": ["500px", "Adobe", "B2BUSABusinesses", "Bitly", "GeekedIn", "HauteLook", "Kickstarter", "LeadHunter", "LinkedIn", "OnlinerSpambot", "PDL", "RiverCityMedia", "VerificationsIO"]}}, "total-leaks": 13, "average-leaks": 13.0, "maintained": false}, {"package": "coverage", "maintainers": ["ned@nedbatchelder.com"], "last-release": "2020-04-12 21:57:15", "leaks": {"ned@nedbatchelder.com": {"leakNum": 21, "leakWebsites": ["Adobe", "Apollo", "Bitly", "DataCamp", "db8151dd", "Disqus", "Dropbox", "Evite", "GeekedIn", "Kickstarter", "Lastfm", "LinkedIn", "MyHeritage", "MySpace", "NemoWeb", "OnlinerSpambot", "PDL", "Tumblr", "VerificationsIO", "YouveBeenScraped", "Zynga"]}}, "total-leaks": 21, "average-leaks": 21.0, "maintained": true}, {"package": "ujson", "maintainers": [], "last-release": "2020-06-03 16:43:41", "leaks": {}, "total-leaks": 0, "average-leaks": 0.0, "maintained": true}, {"package": "pyzmq", "maintainers": ["zeromq-dev@lists.zeromq.org"], "last-release": "2020-05-07 12:19:59", "leaks": {"zeromq-dev@lists.zeromq.org": {"leakNum": 6, "leakWebsites": ["AntiPublic", "ExploitIn", "LinkedIn", "OnlinerSpambot", "PDL", "VerificationsIO"]}}, "total-leaks": 6, "average-leaks": 6.0, "maintained": true}, {"package": "MarkupSafe", "maintainers": ["contact@palletsprojects.com", "armin.ronacher@active-4.com"], "last-release": "2019-02-24 01:04:50", "leaks": {"contact@palletsprojects.com": {"leakNum": 0, "leakWebsites": []}, "armin.ronacher@active-4.com": {"leakNum": 18, "leakWebsites": ["2844Breaches", "500px", "Adobe", "Bitly", "Collection1", "Disqus", "Dropbox", "EpicGames", "GeekedIn", "HeroesOfNewerth", "Kickstarter", "LinkedIn", "OnlinerSpambot", "Patreon", "PDL", "Tumblr", "VerificationsIO", "WarInc"]}}, "total-leaks": 18, "average-leaks": 9.0, "maintained": false}, {"package": "mypy-boto3", "maintainers": ["vlad.emelianov.nz@gmail.com"], "last-release": "2020-06-15 20:16:57", "leaks": {"vlad.emelianov.nz@gmail.com": {"leakNum": 0, "leakWebsites": []}}, "total-leaks": 0, "average-leaks": 0.0, "maintained": true}, {"package": "decorator", "maintainers": ["michele.simionato@gmail.com"], "last-release": "2020-02-29 05:24:45", "leaks": {"michele.simionato@gmail.com": {"leakNum": 11, "leakWebsites": ["Collection1", "Disqus", "Dropbox", "ExploitIn", "GeekedIn", "LinkedIn", "MangaTraders", "MyHeritage", "NemoWeb", "OnlinerSpambot", "PDL"]}}, "total-leaks": 11, "average-leaks": 11.0, "maintained": true}, {"package": "requests-oauthlib", "maintainers": ["me@kennethreitz.com"], "last-release": "2019-11-06 14:41:48", "leaks": {"me@kennethreitz.com": {"leakNum": 32, "leakWebsites": ["500px", "Adobe", "AntiPublic", "Apollo", "Artsy", "Bitly", "CafePress", "Collection1", "Dailymotion", "Disqus", "Dropbox", "Elance", "ExploitIn", "Gawker", "Kickstarter", "Lastfm", "LinkedIn", "MailRu", "MySpace", "OnlinerSpambot", "PDL", "Pemiblanc", "QuinStreet", "RiverCityMedia", "ShareThis", "Ticketfly", "TrikSpamBotnet", "Trillian", "Tumblr", "VerificationsIO", "Yahoo", "YouveBeenScraped"]}}, "total-leaks": 32, "average-leaks": 32.0, "maintained": true}, {"package": "httplib2", "maintainers": ["joe@bitworking.org"], "last-release": "2020-05-20 20:18:30", "leaks": {"joe@bitworking.org": {"leakNum": 23, "leakWebsites": ["AntiPublic", "Apollo", "B2BUSABusinesses", "CafePress", "Dailymotion", "db8151dd", "Disqus", "EverybodyEdits", "Evite", "Exactis", "GeekedIn", "Houzz", "Lastfm", "LeadHunter", "LinkedIn", "MySpace", "Neopets", "OnlinerSpambot", "PDL", "TrikSpamBotnet", "VerificationsIO", "Whitepages", "YouveBeenScraped"]}}, "total-leaks": 23, "average-leaks": 23.0, "maintained": true}, {"package": "xmltodict", "maintainers": ["martinblech@gmail.com"], "last-release": "2019-02-11 07:00:26", "leaks": {"martinblech@gmail.com": {"leakNum": 20, "leakWebsites": ["Badoo", "Collection1", "Disqus", "Dropbox", "ExploitIn", "GeekedIn", "KayoMoe", "Lastfm", "LinkedIn", "MoneyBookers", "MySpace", "OnlinerSpambot", "PDL", "ShareThis", "Taringa", "Ticketfly", "Tumblr", "VerificationsIO", "YouveBeenScraped", "Zynga"]}}, "total-leaks": 20, "average-leaks": 20.0, "maintained": false}, {"package": "biopython", "maintainers": ["biopython@biopython.org"], "last-release": "2020-05-25 15:58:50", "leaks": {"biopython@biopython.org": {"leakNum": 3, "leakWebsites": ["OnlinerSpambot", "RiverCityMedia", "VerificationsIO"]}}, "total-leaks": 3, "average-leaks": 3.0, "maintained": true}]